HISTORY.md
README.md
setup.cfg
setup.py
src/vimeotools/__init__.py
src/vimeotools/vimeo_base.py
src/vimeotools/vimeo_connection.py
src/vimeotools/vimeo_constants.py
src/vimeotools/vimeo_data.py
src/vimeotools/vimeo_folder.py
src/vimeotools/vimeo_showcase.py
src/vimeotools/vimeo_video.py
src/vimeotools.egg-info/PKG-INFO
src/vimeotools.egg-info/SOURCES.txt
src/vimeotools.egg-info/dependency_links.txt
src/vimeotools.egg-info/requires.txt
src/vimeotools.egg-info/top_level.txt