Metadata-Version: 2.1
Name: vimeotools
Version: 0.0.5
Summary: Tools for Vimeo
Home-page: https://github.com/georgpfolz/vimeotools
Author: Georg Pfolz
Author-email: georg.pfolz@invesy.at
License: MIT License
Project-URL: Bug Tracker, https://github.com/georgpfolz/vimeotools/issues
Project-URL: Documentation, https://georgpfolz.github.io/vimeotools
Classifier: Programming Language :: Python :: 3.8
Classifier: Programming Language :: Python :: 3.9
Classifier: Programming Language :: Python :: 3.11
Classifier: License :: OSI Approved :: MIT License
Classifier: Operating System :: OS Independent
Requires-Python: >=3.8
